nobodywho/__init__.py
nobodywho/__init__.pyi
nobodywho/nobodywho.abi3.so
nobodywho/py.typed
nobodywho.libs/libgomp-273d0f96.so.1
nobodywho.libs/libvulkan-15d56633.so.1
nobodywho-0.6.2.dist-info/METADATA
nobodywho-0.6.2.dist-info/WHEEL
nobodywho-0.6.2.dist-info/RECORD
