Metadata-Version: 2.4
Name: nobodywho
Version: 0.6.2
Summary: Python bindings for nobodywho
Keywords: AI,LLM,Large Language Models,Inference,Tool calling,Local LLM,Local Inference,On-device AI,SLM,Edge AI,Realtime LLM,Sustainable AI,Inference engine,Inference library,Local AI
License: EUPL-1.2
Requires-Python: >=3.10
Project-URL: Documentation, https://docs.nobodywho.ooo/
Project-URL: Homepage, https://nobodywho.ooo/
Project-URL: Repository, https://github.com/nobodywho-ooo/nobodywho
